.travis.yml
AUTHORS
ChangeLog
README.md
TESTING.md
requirements.txt
setup.cfg
setup.py
test-requirements.txt
debian/changelog
debian/clean
debian/compat
debian/control
debian/keystone-voms-doc.doc-base
debian/keystone-voms-doc.docs
debian/python-keystone-voms.install
debian/rules
debian/keystone/etc/keystone/voms.json
debian/source/format
doc/Makefile
doc/source/conf.py
doc/source/configuration.rst
doc/source/index.rst
doc/source/installation.rst
doc/source/keystone_voms.rst
doc/source/overview.rst
doc/source/requirements.rst
doc/source/test.rst
doc/source/troubleshooting.rst
doc/source/usage.rst
etc/voms.json
keystone_voms/__init__.py
keystone_voms/core.py
keystone_voms/voms_helper.py
python_keystone_voms.egg-info/PKG-INFO
python_keystone_voms.egg-info/SOURCES.txt
python_keystone_voms.egg-info/dependency_links.txt
python_keystone_voms.egg-info/entry_points.txt
python_keystone_voms.egg-info/not-zip-safe
python_keystone_voms.egg-info/requires.txt
python_keystone_voms.egg-info/top_level.txt
tests/test_middleware_voms_authn.py
tests/config_files/keystone_voms.conf
tests/config_files/voms.json
tests/config_files/voms_no_tenant.json
tests/config_files/voms_no_vo.json